setup.py
doclever2md/__init__.py
doclever2md/main.py
doclever2md.egg-info/PKG-INFO
doclever2md.egg-info/SOURCES.txt
doclever2md.egg-info/dependency_links.txt
doclever2md.egg-info/entry_points.txt
doclever2md.egg-info/requires.txt
doclever2md.egg-info/top_level.txt
doclever2md/tpl/__init__.py
doclever2md/tpl/api_template.md